[
  {
    "codigo": 0,
    "nombre": "COVID-19",
    "edad_recomendacion": {
      "Recien nacido": 10,
      "1 mes": 10,
      "2 meses": 10,
      "4 meses": 10,
      "6 meses": 6,
      "7 meses": 10,
      "9 meses": 6,
      "12 meses": 6,
      "15 meses": 6,
      "18 meses": 6,
      "19-23 meses": 6,
      "2-3 años": 3,
      "4 años": 3,
      "5 años": 3,
      "6 años": 3,
      "7-8 años": 3,
      "9 años": 3,
      "10 años": 3,
      "11-12 años": 3,
      "13-15 años": 3,
      "16 años": 3,
      "17 años": 3,
      "18 años": 6,
      "19-26 años": 6,
      "27-45 años": 6,
      "45-49 años": 6,
      "50-59 años": 6,
      "60-64 años": 6,
      ">65 años": 6,
      ">65 años.1": 6
    },
    "condiciones_medicas": {
      "Embarazo": 6,
      "Malformación congénita del tracto gastrointestinal": 10,
      "Mujer": 6,
      "Inmunocomprometidos (Excluyndo VIH)": 7,
      "Infección VIH  Conteo CD4 <15% or <200mm3": 7,
      "Infección VIH  Conteo ≥15% and ≥200mm3": 6,
      "Asplenia, deficiencias del complemento": 6,
      "Enfermedad renal terminal o en hemodiálisis": 6,
      "Enfermedad cardíaca o enfermedad pulmonar o Alcoholismo": 6,
      "Enfermedad hepática crónica": 6,
      "Diabetes": 6,
      "Zonas endémicas": 6,
      "Personal de salud": 6,
      "Hombres que tienen relaciones sexuales con hombres": 6,
      "Alergia al huevo (Reacción severa)": 10,
      "Reacción alérgica a algun componente de la vacuna": -1,
      "Enfermedad aguda moderada o grave, con o sin fiebre": 3
    },
    "cobertura_pai": {
      "Recien nacido": 0,
      "1 mes": 0,
      "2 meses": 0,
      "4 meses": 0,
      "6 meses": 0,
      "7 meses": 0,
      "9 meses": 0,
      "12 meses": 0,
      "15 meses": 0,
      "18 meses": 0,
      "19-23 meses": 0,
      "2-3 años": 0,
      "4 años": 0,
      "5 años": 0,
      "6 años": 0,
      "7-8 años": 0,
      "9 años": 0,
      "10 años": 0,
      "11-12 años": 0,
      "13-15 años": 0,
      "16 años": 0,
      "17 años": 0,
      "18 años": 0,
      "19-26 años": 0,
      "27-45 años": 0,
      "45-49 años": 0,
      "50-59 años": 0,
      "60-64 años": 0,
      ">65 años": 0
    }
  },
  {
    "codigo": 1,
    "nombre": "BCG",
    "edad_recomendacion": {
      "Recien nacido": 6,
      "1 mes": 10,
      "2 meses": 10,
      "4 meses": 10,
      "6 meses": 10,
      "7 meses": 10,
      "9 meses": 10,
      "12 meses": 10,
      "15 meses": 10,
      "18 meses": 10,
      "19-23 meses": 10,
      "2-3 años": 10,
      "4 años": 10,
      "5 años": 10,
      "6 años": 10,
      "7-8 años": 10,
      "9 años": 10,
      "10 años": 10,
      "11-12 años": 10,
      "13-15 años": 10,
      "16 años": 10,
      "17 años": 10,
      "18 años": 10,
      "19-26 años": 4,
      "27-45 años": 4,
      "45-49 años": 4,
      "50-59 años": 4,
      "60-64 años": 4,
      ">65 años": 4,
      ">65 años.1": 4
    },
    "condiciones_medicas": {
      "Embarazo": -1,
      "Malformación congénita del tracto gastrointestinal": 10,
      "Mujer": 10,
      "Inmunocomprometidos (Excluyndo VIH)": -1,
      "Infección VIH  Conteo CD4 <15% or <200mm3": -1,
      "Infección VIH  Conteo ≥15% and ≥200mm3": -1,
      "Asplenia, deficiencias del complemento": 10,
      "Enfermedad renal terminal o en hemodiálisis": 10,
      "Enfermedad cardíaca o enfermedad pulmonar o Alcoholismo": 10,
      "Enfermedad hepática crónica": 10,
      "Diabetes": 10,
      "Zonas endémicas": 10,
      "Personal de salud": 3,
      "Hombres que tienen relaciones sexuales con hombres": 10,
      "Alergia al huevo (Reacción severa)": 10,
      "Reacción alérgica a algun componente de la vacuna": -1,
      "Enfermedad aguda moderada o grave, con o sin fiebre": 3
    },
    "cobertura_pai": {
      "Recien nacido": 1,
      "1 mes": 0,
      "2 meses": 0,
      "4 meses": 0,
      "6 meses": 0,
      "7 meses": 0,
      "9 meses": 0,
      "12 meses": 5,
      "15 meses": 5,
      "18 meses": 5,
      "19-23 meses": 5,
      "2-3 años": 0,
      "4 años": 5,
      "5 años": 5,
      "6 años": 0,
      "7-8 años": 0,
      "9 años": 0,
      "10 años": 0,
      "11-12 años": 0,
      "13-15 años": 0,
      "16 años": 0,
      "17 años": 0,
      "18 años": 0,
      "19-26 años": 0,
      "27-45 años": 0,
      "45-49 años": 0,
      "50-59 años": 0,
      "60-64 años": 0,
      ">65 años": 0
    }
  },
  {
    "codigo": 2,
    "nombre": "Haemophilus influenzae (Hib)",
    "edad_recomendacion": {
      "Recien nacido": -1,
      "1 mes": -1,
      "2 meses": 6,
      "4 meses": 6,
      "6 meses": 6,
      "7 meses": 5,
      "9 meses": 5,
      "12 meses": 6,
      "15 meses": 6,
      "18 meses": 5,
      "19-23 meses": 5,
      "2-3 años": 5,
      "4 años": 5,
      "5 años": 4,
      "6 años": 4,
      "7-8 años": 4,
      "9 años": 4,
      "10 años": 4,
      "11-12 años": 4,
      "13-15 años": 4,
      "16 años": 4,
      "17 años": 4,
      "18 años": 4,
      "19-26 años": 4,
      "27-45 años": 4,
      "45-49 años": 4,
      "50-59 años": 4,
      "60-64 años": 4,
      ">65 años": 4,
      ">65 años.1": 4
    },
    "condiciones_medicas": {
      "Embarazo": 10,
      "Malformación congénita del tracto gastrointestinal": 10,
      "Mujer": 10,
      "Inmunocomprometidos (Excluyndo VIH)": 7,
      "Infección VIH  Conteo CD4 <15% or <200mm3": 6,
      "Infección VIH  Conteo ≥15% and ≥200mm3": 6,
      "Asplenia, deficiencias del complemento": 6,
      "Enfermedad renal terminal o en hemodiálisis": 6,
      "Enfermedad cardíaca o enfermedad pulmonar o Alcoholismo": 6,
      "Enfermedad hepática crónica": 6,
      "Diabetes": 6,
      "Zonas endémicas": 10,
      "Personal de salud": 4,
      "Hombres que tienen relaciones sexuales con hombres": 4,
      "Alergia al huevo (Reacción severa)": 10,
      "Reacción alérgica a algun componente de la vacuna": -1,
      "Enfermedad aguda moderada o grave, con o sin fiebre": 3
    },
    "cobertura_pai": {
      "Recien nacido": 0,
      "1 mes": 0,
      "2 meses": 0,
      "4 meses": 0,
      "6 meses": 0,
      "7 meses": 0,
      "9 meses": 0,
      "12 meses": 0,
      "15 meses": 0,
      "18 meses": 0,
      "19-23 meses": 0,
      "2-3 años": 0,
      "4 años": 0,
      "5 años": 0,
      "6 años": 0,
      "7-8 años": 0,
      "9 años": 0,
      "10 años": 0,
      "11-12 años": 0,
      "13-15 años": 0,
      "16 años": 0,
      "17 años": 0,
      "18 años": 0,
      "19-26 años": 0,
      "27-45 años": 0,
      "45-49 años": 0,
      "50-59 años": 0,
      "60-64 años": 0,
      ">65 años": 0
    }
  },
  {
    "codigo": 3,
    "nombre": "Hepatitis B (HepB)",
    "edad_recomendacion": {
      "Recien nacido": 6,
      "1 mes": 6,
      "2 meses": 6,
      "4 meses": 4,
      "6 meses": 6,
      "7 meses": 5,
      "9 meses": 6,
      "12 meses": 6,
      "15 meses": 6,
      "18 meses": 5,
      "19-23 meses": 5,
      "2-3 años": 5,
      "4 años": 5,
      "5 años": 5,
      "6 años": 5,
      "7-8 años": 5,
      "9 años": 5,
      "10 años": 5,
      "11-12 años": 5,
      "13-15 años": 5,
      "16 años": 5,
      "17 años": 5,
      "18 años": 5,
      "19-26 años": 5,
      "27-45 años": 5,
      "45-49 años": 5,
      "50-59 años": 5,
      "60-64 años": 3,
      ">65 años": 4,
      ">65 años.1": 4
    },
    "condiciones_medicas": {
      "Embarazo": 6,
      "Malformación congénita del tracto gastrointestinal": 10,
      "Mujer": 6,
      "Inmunocomprometidos (Excluyndo VIH)": 4,
      "Infección VIH  Conteo CD4 <15% or <200mm3": 6,
      "Infección VIH  Conteo ≥15% and ≥200mm3": 6,
      "Asplenia, deficiencias del complemento": 4,
      "Enfermedad renal terminal o en hemodiálisis": 6,
      "Enfermedad cardíaca o enfermedad pulmonar o Alcoholismo": 4,
      "Enfermedad hepática crónica": 6,
      "Diabetes": 3,
      "Zonas endémicas": 6,
      "Personal de salud": 6,
      "Hombres que tienen relaciones sexuales con hombres": 6,
      "Alergia al huevo (Reacción severa)": 10,
      "Reacción alérgica a algun componente de la vacuna": -1,
      "Enfermedad aguda moderada o grave, con o sin fiebre": 3
    },
    "cobertura_pai": {
      "Recien nacido": 1,
      "1 mes": 0,
      "2 meses": 0,
      "4 meses": 0,
      "6 meses": 0,
      "7 meses": 0,
      "9 meses": 0,
      "12 meses": 0,
      "15 meses": 0,
      "18 meses": 0,
      "19-23 meses": 0,
      "2-3 años": 0,
      "4 años": 5,
      "5 años": 5,
      "6 años": 0,
      "7-8 años": 0,
      "9 años": 0,
      "10 años": 0,
      "11-12 años": 0,
      "13-15 años": 0,
      "16 años": 0,
      "17 años": 0,
      "18 años": 0,
      "19-26 años": 0,
      "27-45 años": 0,
      "45-49 años": 0,
      "50-59 años": 0,
      "60-64 años": 0,
      ">65 años": 0
    }
  },
  {
    "codigo": 4,
    "nombre": "DPT (Difteria tosferina Tétanos)",
    "edad_recomendacion": {
      "Recien nacido": 10,
      "1 mes": 10,
      "2 meses": 6,
      "4 meses": 6,
      "6 meses": 6,
      "7 meses": 5,
      "9 meses": 5,
      "12 meses": 5,
      "15 meses": 6,
      "18 meses": 6,
      "19-23 meses": 5,
      "2-3 años": 5,
      "4 años": 10,
      "5 años": 10,
      "6 años": 10,
      "7-8 años": 10,
      "9 años": 10,
      "10 años": 10,
      "11-12 años": 10,
      "13-15 años": 10,
      "16 años": 10,
      "17 años": 10,
      "18 años": 10,
      "19-26 años": 10,
      "27-45 años": 10,
      "45-49 años": 10,
      "50-59 años": 10,
      "60-64 años": 10,
      ">65 años": 10,
      ">65 años.1": 10
    },
    "condiciones_medicas": {
      "Embarazo": 10,
      "Malformación congénita del tracto gastrointestinal": 10,
      "Mujer": 10,
      "Inmunocomprometidos (Excluyndo VIH)": 10,
      "Infección VIH  Conteo CD4 <15% or <200mm3": 10,
      "Infección VIH  Conteo ≥15% and ≥200mm3": 10,
      "Asplenia, deficiencias del complemento": 10,
      "Enfermedad renal terminal o en hemodiálisis": 10,
      "Enfermedad cardíaca o enfermedad pulmonar o Alcoholismo": 10,
      "Enfermedad hepática crónica": 10,
      "Diabetes": 10,
      "Zonas endémicas": 10,
      "Personal de salud": 10,
      "Hombres que tienen relaciones sexuales con hombres": 10,
      "Alergia al huevo (Reacción severa)": 10,
      "Reacción alérgica a algun componente de la vacuna": -1,
      "Enfermedad aguda moderada o grave, con o sin fiebre": 3
    },
    "cobertura_pai": {
      "Recien nacido": 0,
      "1 mes": 0,
      "2 meses": 0,
      "4 meses": 0,
      "6 meses": 0,
      "7 meses": 0,
      "9 meses": 0,
      "12 meses": 0,
      "15 meses": 0,
      "18 meses": 0,
      "19-23 meses": 0,
      "2-3 años": 0,
      "4 años": 5,
      "5 años": 1,
      "6 años": 0,
      "7-8 años": 0,
      "9 años": 0,
      "10 años": 0,
      "11-12 años": 0,
      "13-15 años": 0,
      "16 años": 0,
      "17 años": 0,
      "18 años": 0,
      "19-26 años": 0,
      "27-45 años": 0,
      "45-49 años": 0,
      "50-59 años": 0,
      "60-64 años": 0,
      ">65 años": 0
    }
  },
  {
    "codigo": 5,
    "nombre": "Toxoide tetánico y diftérico del adulto (TD)",
    "edad_recomendacion": {
      "Recien nacido": 10,
      "1 mes": 10,
      "2 meses": 10,
      "4 meses": 10,
      "6 meses": 10,
      "7 meses": 10,
      "9 meses": 10,
      "12 meses": 10,
      "15 meses": 10,
      "18 meses": 10,
      "19-23 meses": 10,
      "2-3 años": 10,
      "4 años": 10,
      "5 años": 10,
      "6 años": 10,
      "7-8 años": 5,
      "9 años": 5,
      "10 años": 5,
      "11-12 años": 5,
      "13-15 años": 5,
      "16 años": 5,
      "17 años": 10,
      "18 años": 10,
      "19-26 años": 5,
      "27-45 años": 4,
      "45-49 años": 4,
      "50-59 años": 4,
      "60-64 años": 4,
      ">65 años": 6,
      ">65 años.1": 6
    },
    "condiciones_medicas": {
      "Embarazo": 7,
      "Malformación congénita del tracto gastrointestinal": 10,
      "Mujer": 6,
      "Inmunocomprometidos (Excluyndo VIH)": 6,
      "Infección VIH  Conteo CD4 <15% or <200mm3": 6,
      "Infección VIH  Conteo ≥15% and ≥200mm3": 6,
      "Asplenia, deficiencias del complemento": 6,
      "Enfermedad renal terminal o en hemodiálisis": 6,
      "Enfermedad cardíaca o enfermedad pulmonar o Alcoholismo": 6,
      "Enfermedad hepática crónica": 6,
      "Diabetes": 6,
      "Zonas endémicas": 10,
      "Personal de salud": 6,
      "Hombres que tienen relaciones sexuales con hombres": 6,
      "Alergia al huevo (Reacción severa)": 10,
      "Reacción alérgica a algun componente de la vacuna": -1,
      "Enfermedad aguda moderada o grave, con o sin fiebre": 3
    },
    "cobertura_pai": {
      "Recien nacido": 0,
      "1 mes": 0,
      "2 meses": 0,
      "4 meses": 0,
      "6 meses": 0,
      "7 meses": 0,
      "9 meses": 0,
      "12 meses": 0,
      "15 meses": 0,
      "18 meses": 0,
      "19-23 meses": 0,
      "2-3 años": 0,
      "4 años": 0,
      "5 años": 0,
      "6 años": 0,
      "7-8 años": 0,
      "9 años": 0,
      "10 años": 0,
      "11-12 años": 0,
      "13-15 años": 0,
      "16 años": 0,
      "17 años": 0,
      "18 años": 0,
      "19-26 años": 0,
      "27-45 años": 0,
      "45-49 años": 0,
      "50-59 años": 0,
      "60-64 años": 0,
      ">65 años": 0
    }
  },
  {
    "codigo": 6,
    "nombre": "Tétanos Difteria-Tosferina Acelular (TdaP)",
    "edad_recomendacion": {
      "Recien nacido": 10,
      "1 mes": 10,
      "2 meses": 10,
      "4 meses": 10,
      "6 meses": 10,
      "7 meses": 10,
      "9 meses": 10,
      "12 meses": 10,
      "15 meses": 10,
      "18 meses": 10,
      "19-23 meses": 10,
      "2-3 años": 10,
      "4 años": 10,
      "5 años": 10,
      "6 años": 10,
      "7-8 años": 5,
      "9 años": 5,
      "10 años": 5,
      "11-12 años": 6,
      "13-15 años": 4,
      "16 años": 4,
      "17 años": 10,
      "18 años": 10,
      "19-26 años": 4,
      "27-45 años": 4,
      "45-49 años": 4,
      "50-59 años": 6,
      "60-64 años": 6,
      ">65 años": 6,
      ">65 años.1": 6
    },
    "condiciones_medicas": {
      "Embarazo": 7,
      "Malformación congénita del tracto gastrointestinal": 10,
      "Mujer": 10,
      "Inmunocomprometidos (Excluyndo VIH)": 6,
      "Infección VIH  Conteo CD4 <15% or <200mm3": 6,
      "Infección VIH  Conteo ≥15% and ≥200mm3": 6,
      "Asplenia, deficiencias del complemento": 6,
      "Enfermedad renal terminal o en hemodiálisis": 6,
      "Enfermedad cardíaca o enfermedad pulmonar o Alcoholismo": 6,
      "Enfermedad hepática crónica": 6,
      "Diabetes": 6,
      "Zonas endémicas": 10,
      "Personal de salud": 6,
      "Hombres que tienen relaciones sexuales con hombres": 6,
      "Alergia al huevo (Reacción severa)": 10,
      "Reacción alérgica a algun componente de la vacuna": -1,
      "Enfermedad aguda moderada o grave, con o sin fiebre": 3
    },
    "cobertura_pai": {
      "Recien nacido": 0,
      "1 mes": 0,
      "2 meses": 0,
      "4 meses": 0,
      "6 meses": 0,
      "7 meses": 0,
      "9 meses": 0,
      "12 meses": 0,
      "15 meses": 0,
      "18 meses": 0,
      "19-23 meses": 0,
      "2-3 años": 0,
      "4 años": 0,
      "5 años": 0,
      "6 años": 0,
      "7-8 años": 0,
      "9 años": 0,
      "10 años": 0,
      "11-12 años": 0,
      "13-15 años": 0,
      "16 años": 0,
      "17 años": 0,
      "18 años": 0,
      "19-26 años": 0,
      "27-45 años": 0,
      "45-49 años": 0,
      "50-59 años": 0,
      "60-64 años": 0,
      ">65 años": 0
    }
  },
  {
    "codigo": 7,
    "nombre": "SRP (Sarampión-Rubéola-paperas)",
    "edad_recomendacion": {
      "Recien nacido": 10,
      "1 mes": 10,
      "2 meses": 10,
      "4 meses": 10,
      "6 meses": 4,
      "7 meses": 10,
      "9 meses": 4,
      "12 meses": 6,
      "15 meses": 6,
      "18 meses": 5,
      "19-23 meses": 5,
      "2-3 años": 5,
      "4 años": 6,
      "5 años": 6,
      "6 años": 6,
      "7-8 años": 5,
      "9 años": 5,
      "10 años": 5,
      "11-12 años": 5,
      "13-15 años": 4,
      "16 años": 4,
      "17 años": 5,
      "18 años": 5,
      "19-26 años": 5,
      "27-45 años": 5,
      "45-49 años": 5,
      "50-59 años": 5,
      "60-64 años": 5,
      ">65 años": 6,
      ">65 años.1": 6
    },
    "condiciones_medicas": {
      "Embarazo": -1,
      "Malformación congénita del tracto gastrointestinal": 10,
      "Mujer": 10,
      "Inmunocomprometidos (Excluyndo VIH)": -1,
      "Infección VIH  Conteo CD4 <15% or <200mm3": -1,
      "Infección VIH  Conteo ≥15% and ≥200mm3": 6,
      "Asplenia, deficiencias del complemento": 6,
      "Enfermedad renal terminal o en hemodiálisis": 6,
      "Enfermedad cardíaca o enfermedad pulmonar o Alcoholismo": 6,
      "Enfermedad hepática crónica": 6,
      "Diabetes": 6,
      "Zonas endémicas": 10,
      "Personal de salud": 6,
      "Hombres que tienen relaciones sexuales con hombres": 6,
      "Alergia al huevo (Reacción severa)": 2,
      "Reacción alérgica a algun componente de la vacuna": -1,
      "Enfermedad aguda moderada o grave, con o sin fiebre": 3
    },
    "cobertura_pai": {
      "Recien nacido": 0,
      "1 mes": 0,
      "2 meses": 0,
      "4 meses": 0,
      "6 meses": 0,
      "7 meses": 0,
      "9 meses": 0,
      "12 meses": 1,
      "15 meses": 5,
      "18 meses": 1,
      "19-23 meses": 5,
      "2-3 años": 0,
      "4 años": 5,
      "5 años": 5,
      "6 años": 0,
      "7-8 años": 0,
      "9 años": 0,
      "10 años": 0,
      "11-12 años": 0,
      "13-15 años": 0,
      "16 años": 0,
      "17 años": 0,
      "18 años": 0,
      "19-26 años": 0,
      "27-45 años": 0,
      "45-49 años": 0,
      "50-59 años": 0,
      "60-64 años": 0,
      ">65 años": 0
    }
  },
  {
    "codigo": 8,
    "nombre": "Varicela (VAR)",
    "edad_recomendacion": {
      "Recien nacido": 10,
      "1 mes": 10,
      "2 meses": 10,
      "4 meses": 10,
      "6 meses": 10,
      "7 meses": 10,
      "9 meses": 10,
      "12 meses": 6,
      "15 meses": 6,
      "18 meses": 5,
      "19-23 meses": 5,
      "2-3 años": 5,
      "4 años": 6,
      "5 años": 6,
      "6 años": 6,
      "7-8 años": 5,
      "9 años": 5,
      "10 años": 5,
      "11-12 años": 5,
      "13-15 años": 5,
      "16 años": 5,
      "17 años": 5,
      "18 años": 5,
      "19-26 años": 5,
      "27-45 años": 4,
      "45-49 años": 4,
      "50-59 años": 4,
      "60-64 años": 4,
      ">65 años": 4,
      ">65 años.1": 4
    },
    "condiciones_medicas": {
      "Embarazo": -1,
      "Malformación congénita del tracto gastrointestinal": 10,
      "Mujer": 10,
      "Inmunocomprometidos (Excluyndo VIH)": -1,
      "Infección VIH  Conteo CD4 <15% or <200mm3": -1,
      "Infección VIH  Conteo ≥15% and ≥200mm3": 6,
      "Asplenia, deficiencias del complemento": 6,
      "Enfermedad renal terminal o en hemodiálisis": 6,
      "Enfermedad cardíaca o enfermedad pulmonar o Alcoholismo": 6,
      "Enfermedad hepática crónica": 6,
      "Diabetes": 6,
      "Zonas endémicas": 10,
      "Personal de salud": 6,
      "Hombres que tienen relaciones sexuales con hombres": 6,
      "Alergia al huevo (Reacción severa)": 10,
      "Reacción alérgica a algun componente de la vacuna": -1,
      "Enfermedad aguda moderada o grave, con o sin fiebre": 3
    },
    "cobertura_pai": {
      "Recien nacido": 0,
      "1 mes": 0,
      "2 meses": 0,
      "4 meses": 0,
      "6 meses": 0,
      "7 meses": 0,
      "9 meses": 0,
      "12 meses": 1,
      "15 meses": 5,
      "18 meses": 5,
      "19-23 meses": 5,
      "2-3 años": 0,
      "4 años": 5,
      "5 años": 1,
      "6 años": 0,
      "7-8 años": 0,
      "9 años": 0,
      "10 años": 0,
      "11-12 años": 0,
      "13-15 años": 0,
      "16 años": 0,
      "17 años": 0,
      "18 años": 0,
      "19-26 años": 0,
      "27-45 años": 0,
      "45-49 años": 0,
      "50-59 años": 0,
      "60-64 años": 0,
      ">65 años": 0
    }
  },
  {
    "codigo": 9,
    "nombre": "Zoster recombinante (RZV)",
    "edad_recomendacion": {
      "Recien nacido": 10,
      "1 mes": 10,
      "2 meses": 10,
      "4 meses": 10,
      "6 meses": 10,
      "7 meses": 10,
      "9 meses": 10,
      "12 meses": 10,
      "15 meses": 10,
      "18 meses": 10,
      "19-23 meses": 10,
      "2-3 años": 10,
      "4 años": 10,
      "5 años": 10,
      "6 años": 10,
      "7-8 años": 10,
      "9 años": 10,
      "10 años": 10,
      "11-12 años": 10,
      "13-15 años": 10,
      "16 años": 10,
      "17 años": 10,
      "18 años": 10,
      "19-26 años": 4,
      "27-45 años": 4,
      "45-49 años": 4,
      "50-59 años": 6,
      "60-64 años": 6,
      ">65 años": 6,
      ">65 años.1": 6
    },
    "condiciones_medicas": {
      "Embarazo": 10,
      "Malformación congénita del tracto gastrointestinal": 10,
      "Mujer": 10,
      "Inmunocomprometidos (Excluyndo VIH)": 6,
      "Infección VIH  Conteo CD4 <15% or <200mm3": 6,
      "Infección VIH  Conteo ≥15% and ≥200mm3": 6,
      "Asplenia, deficiencias del complemento": 4,
      "Enfermedad renal terminal o en hemodiálisis": 4,
      "Enfermedad cardíaca o enfermedad pulmonar o Alcoholismo": 4,
      "Enfermedad hepática crónica": 4,
      "Diabetes": 4,
      "Zonas endémicas": 10,
      "Personal de salud": 4,
      "Hombres que tienen relaciones sexuales con hombres": 4,
      "Alergia al huevo (Reacción severa)": 10,
      "Reacción alérgica a algun componente de la vacuna": -1,
      "Enfermedad aguda moderada o grave, con o sin fiebre": 3
    },
    "cobertura_pai": {
      "Recien nacido": 0,
      "1 mes": 0,
      "2 meses": 0,
      "4 meses": 0,
      "6 meses": 0,
      "7 meses": 0,
      "9 meses": 0,
      "12 meses": 0,
      "15 meses": 0,
      "18 meses": 0,
      "19-23 meses": 0,
      "2-3 años": 0,
      "4 años": 0,
      "5 años": 0,
      "6 años": 0,
      "7-8 años": 0,
      "9 años": 0,
      "10 años": 0,
      "11-12 años": 0,
      "13-15 años": 0,
      "16 años": 0,
      "17 años": 0,
      "18 años": 0,
      "19-26 años": 0,
      "27-45 años": 0,
      "45-49 años": 0,
      "50-59 años": 0,
      "60-64 años": 0,
      ">65 años": 0
    }
  },
  {
    "codigo": 10,
    "nombre": "Virus del papiloma humano (VPH)",
    "edad_recomendacion": {
      "Recien nacido": 10,
      "1 mes": 10,
      "2 meses": 10,
      "4 meses": 10,
      "6 meses": 10,
      "7 meses": 10,
      "9 meses": 10,
      "12 meses": 10,
      "15 meses": 10,
      "18 meses": 10,
      "19-23 meses": 10,
      "2-3 años": 10,
      "4 años": 10,
      "5 años": 10,
      "6 años": 10,
      "7-8 años": 10,
      "9 años": 3,
      "10 años": 3,
      "11-12 años": 6,
      "13-15 años": 5,
      "16 años": 5,
      "17 años": 5,
      "18 años": 5,
      "19-26 años": 5,
      "27-45 años": 3,
      "45-49 años": 3,
      "50-59 años": 10,
      "60-64 años": 10,
      ">65 años": 10,
      ">65 años.1": 10
    },
    "condiciones_medicas": {
      "Embarazo": -1,
      "Malformación congénita del tracto gastrointestinal": 10,
      "Mujer": 6,
      "Inmunocomprometidos (Excluyndo VIH)": 7,
      "Infección VIH  Conteo CD4 <15% or <200mm3": 7,
      "Infección VIH  Conteo ≥15% and ≥200mm3": 7,
      "Asplenia, deficiencias del complemento": 4,
      "Enfermedad renal terminal o en hemodiálisis": 7,
      "Enfermedad cardíaca o enfermedad pulmonar o Alcoholismo": 4,
      "Enfermedad hepática crónica": 4,
      "Diabetes": 4,
      "Zonas endémicas": 10,
      "Personal de salud": 4,
      "Hombres que tienen relaciones sexuales con hombres": 4,
      "Alergia al huevo (Reacción severa)": 10,
      "Reacción alérgica a algun componente de la vacuna": -1,
      "Enfermedad aguda moderada o grave, con o sin fiebre": 3
    },
    "cobertura_pai": {
      "Recien nacido": 0,
      "1 mes": 0,
      "2 meses": 0,
      "4 meses": 0,
      "6 meses": 0,
      "7 meses": 0,
      "9 meses": 0,
      "12 meses": 0,
      "15 meses": 0,
      "18 meses": 0,
      "19-23 meses": 0,
      "2-3 años": 0,
      "4 años": 0,
      "5 años": 0,
      "6 años": 0,
      "7-8 años": 0,
      "9 años": 1,
      "10 años": 1,
      "11-12 años": 1,
      "13-15 años": 1,
      "16 años": 1,
      "17 años": 1,
      "18 años": 0,
      "19-26 años": 0,
      "27-45 años": 0,
      "45-49 años": 0,
      "50-59 años": 0,
      "60-64 años": 0,
      ">65 años": 0
    }
  },
  {
    "codigo": 11,
    "nombre": "Neumococo (Conjugada-PCV10, PCV13, PCV15, PCV20)",
    "edad_recomendacion": {
      "Recien nacido": 10,
      "1 mes": 10,
      "2 meses": 6,
      "4 meses": 6,
      "6 meses": 6,
      "7 meses": 5,
      "9 meses": 5,
      "12 meses": 6,
      "15 meses": 6,
      "18 meses": 5,
      "19-23 meses": 5,
      "2-3 años": 5,
      "4 años": 5,
      "5 años": 4,
      "6 años": 4,
      "7-8 años": 4,
      "9 años": 4,
      "10 años": 4,
      "11-12 años": 4,
      "13-15 años": 4,
      "16 años": 4,
      "17 años": 4,
      "18 años": 4,
      "19-26 años": 4,
      "27-45 años": 4,
      "45-49 años": 4,
      "50-59 años": 4,
      "60-64 años": 4,
      ">65 años": 6,
      ">65 años.1": 6
    },
    "condiciones_medicas": {
      "Embarazo": 10,
      "Malformación congénita del tracto gastrointestinal": 10,
      "Mujer": 10,
      "Inmunocomprometidos (Excluyndo VIH)": 7,
      "Infección VIH  Conteo CD4 <15% or <200mm3": 7,
      "Infección VIH  Conteo ≥15% and ≥200mm3": 7,
      "Asplenia, deficiencias del complemento": 7,
      "Enfermedad renal terminal o en hemodiálisis": 7,
      "Enfermedad cardíaca o enfermedad pulmonar o Alcoholismo": 7,
      "Enfermedad hepática crónica": 7,
      "Diabetes": 7,
      "Zonas endémicas": 10,
      "Personal de salud": 4,
      "Hombres que tienen relaciones sexuales con hombres": 4,
      "Alergia al huevo (Reacción severa)": 10,
      "Reacción alérgica a algun componente de la vacuna": -1,
      "Enfermedad aguda moderada o grave, con o sin fiebre": 3
    },
    "cobertura_pai": {
      "Recien nacido": 0,
      "1 mes": 0,
      "2 meses": 1,
      "4 meses": 1,
      "6 meses": 0,
      "7 meses": 0,
      "9 meses": 0,
      "12 meses": 1,
      "15 meses": 5,
      "18 meses": 5,
      "19-23 meses": 5,
      "2-3 años": 0,
      "4 años": 5,
      "5 años": 5,
      "6 años": 0,
      "7-8 años": 0,
      "9 años": 0,
      "10 años": 0,
      "11-12 años": 0,
      "13-15 años": 0,
      "16 años": 0,
      "17 años": 0,
      "18 años": 0,
      "19-26 años": 0,
      "27-45 años": 0,
      "45-49 años": 0,
      "50-59 años": 0,
      "60-64 años": 0,
      ">65 años": 0
    }
  },
  {
    "codigo": 12,
    "nombre": "Neumococo (Polisacarida-PPSV23)",
    "edad_recomendacion": {
      "Recien nacido": 10,
      "1 mes": 10,
      "2 meses": 10,
      "4 meses": 10,
      "6 meses": 10,
      "7 meses": 10,
      "9 meses": 10,
      "12 meses": 10,
      "15 meses": 10,
      "18 meses": 10,
      "19-23 meses": 10,
      "2-3 años": 4,
      "4 años": 10,
      "5 años": 10,
      "6 años": 10,
      "7-8 años": 4,
      "9 años": 4,
      "10 años": 4,
      "11-12 años": 4,
      "13-15 años": 4,
      "16 años": 4,
      "17 años": 10,
      "18 años": 10,
      "19-26 años": 4,
      "27-45 años": 4,
      "45-49 años": 4,
      "50-59 años": 4,
      "60-64 años": 6,
      ">65 años": 6,
      ">65 años.1": 6
    },
    "condiciones_medicas": {
      "Embarazo": 10,
      "Malformación congénita del tracto gastrointestinal": 10,
      "Mujer": 10,
      "Inmunocomprometidos (Excluyndo VIH)": 7,
      "Infección VIH  Conteo CD4 <15% or <200mm3": 7,
      "Infección VIH  Conteo ≥15% and ≥200mm3": 7,
      "Asplenia, deficiencias del complemento": 7,
      "Enfermedad renal terminal o en hemodiálisis": 6,
      "Enfermedad cardíaca o enfermedad pulmonar o Alcoholismo": 7,
      "Enfermedad hepática crónica": 7,
      "Diabetes": 7,
      "Zonas endémicas": 10,
      "Personal de salud": 4,
      "Hombres que tienen relaciones sexuales con hombres": 4,
      "Alergia al huevo (Reacción severa)": 10,
      "Reacción alérgica a algun componente de la vacuna": -1,
      "Enfermedad aguda moderada o grave, con o sin fiebre": 3
    },
    "cobertura_pai": {
      "Recien nacido": 0,
      "1 mes": 0,
      "2 meses": 1,
      "4 meses": 1,
      "6 meses": 0,
      "7 meses": 0,
      "9 meses": 0,
      "12 meses": 1,
      "15 meses": 5,
      "18 meses": 5,
      "19-23 meses": 5,
      "2-3 años": 0,
      "4 años": 5,
      "5 años": 5,
      "6 años": 0,
      "7-8 años": 0,
      "9 años": 0,
      "10 años": 0,
      "11-12 años": 0,
      "13-15 años": 0,
      "16 años": 0,
      "17 años": 0,
      "18 años": 0,
      "19-26 años": 0,
      "27-45 años": 0,
      "45-49 años": 0,
      "50-59 años": 0,
      "60-64 años": 0,
      ">65 años": 0
    }
  },
  {
    "codigo": 13,
    "nombre": "Hepatitis A (HepA)",
    "edad_recomendacion": {
      "Recien nacido": 10,
      "1 mes": 10,
      "2 meses": 10,
      "4 meses": 10,
      "6 meses": 4,
      "7 meses": 10,
      "9 meses": 4,
      "12 meses": 1,
      "15 meses": 6,
      "18 meses": 6,
      "19-23 meses": 6,
      "2-3 años": 5,
      "4 años": 5,
      "5 años": 5,
      "6 años": 5,
      "7-8 años": 5,
      "9 años": 5,
      "10 años": 5,
      "11-12 años": 5,
      "13-15 años": 5,
      "16 años": 5,
      "17 años": 5,
      "18 años": 5,
      "19-26 años": 4,
      "27-45 años": 4,
      "45-49 años": 4,
      "50-59 años": 4,
      "60-64 años": 4,
      ">65 años": 4,
      ">65 años.1": 4
    },
    "condiciones_medicas": {
      "Embarazo": 4,
      "Malformación congénita del tracto gastrointestinal": 10,
      "Mujer": 10,
      "Inmunocomprometidos (Excluyndo VIH)": 6,
      "Infección VIH  Conteo CD4 <15% or <200mm3": 6,
      "Infección VIH  Conteo ≥15% and ≥200mm3": 6,
      "Asplenia, deficiencias del complemento": 6,
      "Enfermedad renal terminal o en hemodiálisis": 6,
      "Enfermedad cardíaca o enfermedad pulmonar o Alcoholismo": 6,
      "Enfermedad hepática crónica": 6,
      "Diabetes": 6,
      "Zonas endémicas": 6,
      "Personal de salud": 6,
      "Hombres que tienen relaciones sexuales con hombres": 6,
      "Alergia al huevo (Reacción severa)": 10,
      "Reacción alérgica a algun componente de la vacuna": -1,
      "Enfermedad aguda moderada o grave, con o sin fiebre": 3
    },
    "cobertura_pai": {
      "Recien nacido": 0,
      "1 mes": 0,
      "2 meses": 0,
      "4 meses": 0,
      "6 meses": 0,
      "7 meses": 0,
      "9 meses": 0,
      "12 meses": 1,
      "15 meses": 5,
      "18 meses": 5,
      "19-23 meses": 5,
      "2-3 años": 0,
      "4 años": 5,
      "5 años": 5,
      "6 años": 0,
      "7-8 años": 0,
      "9 años": 0,
      "10 años": 0,
      "11-12 años": 0,
      "13-15 años": 0,
      "16 años": 0,
      "17 años": 0,
      "18 años": 0,
      "19-26 años": 0,
      "27-45 años": 0,
      "45-49 años": 0,
      "50-59 años": 0,
      "60-64 años": 0,
      ">65 años": 0
    }
  },
  {
    "codigo": 14,
    "nombre": "Meningococo A, C, W, Y",
    "edad_recomendacion": {
      "Recien nacido": 10,
      "1 mes": 10,
      "2 meses": 4,
      "4 meses": 4,
      "6 meses": 4,
      "7 meses": 10,
      "9 meses": 4,
      "12 meses": 4,
      "15 meses": 4,
      "18 meses": 4,
      "19-23 meses": 4,
      "2-3 años": 4,
      "4 años": 4,
      "5 años": 4,
      "6 años": 4,
      "7-8 años": 4,
      "9 años": 4,
      "10 años": 3,
      "11-12 años": 6,
      "13-15 años": 5,
      "16 años": 6,
      "17 años": 5,
      "18 años": 5,
      "19-26 años": 4,
      "27-45 años": 4,
      "45-49 años": 4,
      "50-59 años": 4,
      "60-64 años": 4,
      ">65 años": 4,
      ">65 años.1": 4
    },
    "condiciones_medicas": {
      "Embarazo": 6,
      "Malformación congénita del tracto gastrointestinal": 10,
      "Mujer": 10,
      "Inmunocomprometidos (Excluyndo VIH)": 6,
      "Infección VIH  Conteo CD4 <15% or <200mm3": 7,
      "Infección VIH  Conteo ≥15% and ≥200mm3": 7,
      "Asplenia, deficiencias del complemento": 7,
      "Enfermedad renal terminal o en hemodiálisis": 4,
      "Enfermedad cardíaca o enfermedad pulmonar o Alcoholismo": 6,
      "Enfermedad hepática crónica": 6,
      "Diabetes": 6,
      "Zonas endémicas": 6,
      "Personal de salud": 6,
      "Hombres que tienen relaciones sexuales con hombres": 6,
      "Alergia al huevo (Reacción severa)": 10,
      "Reacción alérgica a algun componente de la vacuna": -1,
      "Enfermedad aguda moderada o grave, con o sin fiebre": 3
    },
    "cobertura_pai": {
      "Recien nacido": 0,
      "1 mes": 0,
      "2 meses": 0,
      "4 meses": 0,
      "6 meses": 0,
      "7 meses": 0,
      "9 meses": 0,
      "12 meses": 0,
      "15 meses": 0,
      "18 meses": 0,
      "19-23 meses": 0,
      "2-3 años": 0,
      "4 años": 0,
      "5 años": 0,
      "6 años": 0,
      "7-8 años": 0,
      "9 años": 0,
      "10 años": 0,
      "11-12 años": 0,
      "13-15 años": 0,
      "16 años": 0,
      "17 años": 0,
      "18 años": 0,
      "19-26 años": 0,
      "27-45 años": 0,
      "45-49 años": 0,
      "50-59 años": 0,
      "60-64 años": 0,
      ">65 años": 0
    }
  },
  {
    "codigo": 15,
    "nombre": "Meningococo B (MenB)",
    "edad_recomendacion": {
      "Recien nacido": 10,
      "1 mes": 10,
      "2 meses": 10,
      "4 meses": 10,
      "6 meses": 10,
      "7 meses": 10,
      "9 meses": 10,
      "12 meses": 10,
      "15 meses": 10,
      "18 meses": 10,
      "19-23 meses": 10,
      "2-3 años": 10,
      "4 años": 10,
      "5 años": 10,
      "6 años": 10,
      "7-8 años": 10,
      "9 años": 4,
      "10 años": 4,
      "11-12 años": 4,
      "13-15 años": 4,
      "16 años": 3,
      "17 años": 4,
      "18 años": 4,
      "19-26 años": 3,
      "27-45 años": 4,
      "45-49 años": 4,
      "50-59 años": 4,
      "60-64 años": 4,
      ">65 años": 4,
      ">65 años.1": 4
    },
    "condiciones_medicas": {
      "Embarazo": 2,
      "Malformación congénita del tracto gastrointestinal": 10,
      "Mujer": 10,
      "Inmunocomprometidos (Excluyndo VIH)": 4,
      "Infección VIH  Conteo CD4 <15% or <200mm3": 4,
      "Infección VIH  Conteo ≥15% and ≥200mm3": 4,
      "Asplenia, deficiencias del complemento": 7,
      "Enfermedad renal terminal o en hemodiálisis": 6,
      "Enfermedad cardíaca o enfermedad pulmonar o Alcoholismo": 4,
      "Enfermedad hepática crónica": 4,
      "Diabetes": 4,
      "Zonas endémicas": 4,
      "Personal de salud": 4,
      "Hombres que tienen relaciones sexuales con hombres": 4,
      "Alergia al huevo (Reacción severa)": 10,
      "Reacción alérgica a algun componente de la vacuna": -1,
      "Enfermedad aguda moderada o grave, con o sin fiebre": 3
    },
    "cobertura_pai": {
      "Recien nacido": 0,
      "1 mes": 0,
      "2 meses": 0,
      "4 meses": 0,
      "6 meses": 0,
      "7 meses": 0,
      "9 meses": 0,
      "12 meses": 0,
      "15 meses": 0,
      "18 meses": 0,
      "19-23 meses": 0,
      "2-3 años": 0,
      "4 años": 0,
      "5 años": 0,
      "6 años": 0,
      "7-8 años": 0,
      "9 años": 0,
      "10 años": 0,
      "11-12 años": 0,
      "13-15 años": 0,
      "16 años": 0,
      "17 años": 0,
      "18 años": 0,
      "19-26 años": 0,
      "27-45 años": 0,
      "45-49 años": 0,
      "50-59 años": 0,
      "60-64 años": 0,
      ">65 años": 0
    }
  },
  {
    "codigo": 16,
    "nombre": "Poliomielitis (Polio)",
    "edad_recomendacion": {
      "Recien nacido": 10,
      "1 mes": 10,
      "2 meses": 6,
      "4 meses": 6,
      "6 meses": 6,
      "7 meses": 5,
      "9 meses": 6,
      "12 meses": 6,
      "15 meses": 6,
      "18 meses": 6,
      "19-23 meses": 5,
      "2-3 años": 5,
      "4 años": 6,
      "5 años": 6,
      "6 años": 6,
      "7-8 años": 5,
      "9 años": 5,
      "10 años": 5,
      "11-12 años": 5,
      "13-15 años": 5,
      "16 años": 5,
      "17 años": 5,
      "18 años": 5,
      "19-26 años": 6,
      "27-45 años": 6,
      "45-49 años": 6,
      "50-59 años": 6,
      "60-64 años": 6,
      ">65 años": 6,
      ">65 años.1": 6
    },
    "condiciones_medicas": {
      "Embarazo": 2,
      "Malformación congénita del tracto gastrointestinal": 6,
      "Mujer": 10,
      "Inmunocomprometidos (Excluyndo VIH)": 6,
      "Infección VIH  Conteo CD4 <15% or <200mm3": 6,
      "Infección VIH  Conteo ≥15% and ≥200mm3": 6,
      "Asplenia, deficiencias del complemento": 6,
      "Enfermedad renal terminal o en hemodiálisis": 6,
      "Enfermedad cardíaca o enfermedad pulmonar o Alcoholismo": 6,
      "Enfermedad hepática crónica": 6,
      "Diabetes": 6,
      "Zonas endémicas": 10,
      "Personal de salud": 6,
      "Hombres que tienen relaciones sexuales con hombres": 6,
      "Alergia al huevo (Reacción severa)": 10,
      "Reacción alérgica a algun componente de la vacuna": -1,
      "Enfermedad aguda moderada o grave, con o sin fiebre": 3
    },
    "cobertura_pai": {
      "Recien nacido": 0,
      "1 mes": 0,
      "2 meses": 1,
      "4 meses": 1,
      "6 meses": 1,
      "7 meses": 0,
      "9 meses": 0,
      "12 meses": 5,
      "15 meses": 5,
      "18 meses": 1,
      "19-23 meses": 5,
      "2-3 años": 0,
      "4 años": 5,
      "5 años": 1,
      "6 años": 0,
      "7-8 años": 0,
      "9 años": 0,
      "10 años": 0,
      "11-12 años": 0,
      "13-15 años": 0,
      "16 años": 0,
      "17 años": 0,
      "18 años": 0,
      "19-26 años": 0,
      "27-45 años": 0,
      "45-49 años": 0,
      "50-59 años": 0,
      "60-64 años": 0,
      ">65 años": 0
    }
  },
  {
    "codigo": 17,
    "nombre": "Rotavirus",
    "edad_recomendacion": {
      "Recien nacido": 10,
      "1 mes": 10,
      "2 meses": 6,
      "4 meses": 6,
      "6 meses": 6,
      "7 meses": 5,
      "9 meses": 5,
      "12 meses": 10,
      "15 meses": 10,
      "18 meses": 10,
      "19-23 meses": 10,
      "2-3 años": 10,
      "4 años": 10,
      "5 años": 10,
      "6 años": 10,
      "7-8 años": 10,
      "9 años": 10,
      "10 años": 10,
      "11-12 años": 10,
      "13-15 años": 10,
      "16 años": 10,
      "17 años": 10,
      "18 años": 10,
      "19-26 años": 10,
      "27-45 años": 10,
      "45-49 años": 10,
      "50-59 años": 10,
      "60-64 años": 10,
      ">65 años": 10,
      ">65 años.1": 10
    },
    "condiciones_medicas": {
      "Embarazo": 10,
      "Malformación congénita del tracto gastrointestinal": -1,
      "Mujer": 10,
      "Inmunocomprometidos (Excluyndo VIH)": -1,
      "Infección VIH  Conteo CD4 <15% or <200mm3": 2,
      "Infección VIH  Conteo ≥15% and ≥200mm3": 2,
      "Asplenia, deficiencias del complemento": 6,
      "Enfermedad renal terminal o en hemodiálisis": 6,
      "Enfermedad cardíaca o enfermedad pulmonar o Alcoholismo": 6,
      "Enfermedad hepática crónica": 6,
      "Diabetes": 6,
      "Zonas endémicas": 10,
      "Personal de salud": 10,
      "Hombres que tienen relaciones sexuales con hombres": 10,
      "Alergia al huevo (Reacción severa)": 10,
      "Reacción alérgica a algun componente de la vacuna": -1,
      "Enfermedad aguda moderada o grave, con o sin fiebre": 3
    },
    "cobertura_pai": {
      "Recien nacido": 0,
      "1 mes": 0,
      "2 meses": 1,
      "4 meses": 1,
      "6 meses": 0,
      "7 meses": 0,
      "9 meses": 0,
      "12 meses": 0,
      "15 meses": 0,
      "18 meses": 0,
      "19-23 meses": 0,
      "2-3 años": 0,
      "4 años": 0,
      "5 años": 0,
      "6 años": 0,
      "7-8 años": 0,
      "9 años": 0,
      "10 años": 0,
      "11-12 años": 0,
      "13-15 años": 0,
      "16 años": 0,
      "17 años": 0,
      "18 años": 0,
      "19-26 años": 0,
      "27-45 años": 0,
      "45-49 años": 0,
      "50-59 años": 0,
      "60-64 años": 0,
      ">65 años": 0
    }
  },
  {
    "codigo": 18,
    "nombre": "Influenza estacional /gripe",
    "edad_recomendacion": {
      "Recien nacido": 10,
      "1 mes": 10,
      "2 meses": 10,
      "4 meses": 10,
      "6 meses": 6,
      "7 meses": 6,
      "9 meses": 6,
      "12 meses": 6,
      "15 meses": 6,
      "18 meses": 6,
      "19-23 meses": 6,
      "2-3 años": 6,
      "4 años": 10,
      "5 años": 10,
      "6 años": 10,
      "7-8 años": 6,
      "9 años": 6,
      "10 años": 6,
      "11-12 años": 6,
      "13-15 años": 6,
      "16 años": 6,
      "17 años": 6,
      "18 años": 6,
      "19-26 años": 6,
      "27-45 años": 6,
      "45-49 años": 6,
      "50-59 años": 6,
      "60-64 años": 6,
      ">65 años": 6,
      ">65 años.1": 6
    },
    "condiciones_medicas": {
      "Embarazo": 6,
      "Malformación congénita del tracto gastrointestinal": 10,
      "Mujer": 10,
      "Inmunocomprometidos (Excluyndo VIH)": 6,
      "Infección VIH  Conteo CD4 <15% or <200mm3": 6,
      "Infección VIH  Conteo ≥15% and ≥200mm3": 6,
      "Asplenia, deficiencias del complemento": 6,
      "Enfermedad renal terminal o en hemodiálisis": 10,
      "Enfermedad cardíaca o enfermedad pulmonar o Alcoholismo": 6,
      "Enfermedad hepática crónica": 6,
      "Diabetes": 6,
      "Zonas endémicas": 10,
      "Personal de salud": 6,
      "Hombres que tienen relaciones sexuales con hombres": 6,
      "Alergia al huevo (Reacción severa)": 2,
      "Reacción alérgica a algun componente de la vacuna": -1,
      "Enfermedad aguda moderada o grave, con o sin fiebre": 3
    },
    "cobertura_pai": {
      "Recien nacido": 0,
      "1 mes": 0,
      "2 meses": 0,
      "4 meses": 0,
      "6 meses": 1,
      "7 meses": 1,
      "9 meses": 0,
      "12 meses": 5,
      "15 meses": 5,
      "18 meses": 5,
      "19-23 meses": 5,
      "2-3 años": 0,
      "4 años": 0,
      "5 años": 0,
      "6 años": 0,
      "7-8 años": 0,
      "9 años": 0,
      "10 años": 0,
      "11-12 años": 0,
      "13-15 años": 0,
      "16 años": 0,
      "17 años": 0,
      "18 años": 0,
      "19-26 años": 0,
      "27-45 años": 0,
      "45-49 años": 0,
      "50-59 años": 0,
      "60-64 años": 0,
      ">65 años": 0
    }
  },
  {
    "codigo": 19,
    "nombre": "Influenza trivalente",
    "edad_recomendacion": {
      "Recien nacido": 10,
      "1 mes": 10,
      "2 meses": 10,
      "4 meses": 10,
      "6 meses": 10,
      "7 meses": 10,
      "9 meses": 10,
      "12 meses": 10,
      "15 meses": 10,
      "18 meses": 10,
      "19-23 meses": 10,
      "2-3 años": 10,
      "4 años": 10,
      "5 años": 10,
      "6 años": 10,
      "7-8 años": 10,
      "9 años": 10,
      "10 años": 10,
      "11-12 años": 10,
      "13-15 años": 10,
      "16 años": 10,
      "17 años": 10,
      "18 años": 10,
      "19-26 años": 10,
      "27-45 años": 10,
      "45-49 años": 10,
      "50-59 años": 10,
      "60-64 años": 10,
      ">65 años": 10,
      ">65 años.1": 10
    },
    "condiciones_medicas": {
      "Embarazo": 10,
      "Malformación congénita del tracto gastrointestinal": 10,
      "Mujer": 10,
      "Inmunocomprometidos (Excluyndo VIH)": 10,
      "Infección VIH  Conteo CD4 <15% or <200mm3": 10,
      "Infección VIH  Conteo ≥15% and ≥200mm3": 10,
      "Asplenia, deficiencias del complemento": 10,
      "Enfermedad renal terminal o en hemodiálisis": 10,
      "Enfermedad cardíaca o enfermedad pulmonar o Alcoholismo": 10,
      "Enfermedad hepática crónica": 10,
      "Diabetes": 10,
      "Zonas endémicas": 10,
      "Personal de salud": 10,
      "Hombres que tienen relaciones sexuales con hombres": 10,
      "Alergia al huevo (Reacción severa)": 10,
      "Reacción alérgica a algun componente de la vacuna": -1,
      "Enfermedad aguda moderada o grave, con o sin fiebre": 3
    },
    "cobertura_pai": {
      "Recien nacido": 0,
      "1 mes": 0,
      "2 meses": 0,
      "4 meses": 0,
      "6 meses": 0,
      "7 meses": 0,
      "9 meses": 0,
      "12 meses": 0,
      "15 meses": 0,
      "18 meses": 0,
      "19-23 meses": 0,
      "2-3 años": 0,
      "4 años": 0,
      "5 años": 0,
      "6 años": 0,
      "7-8 años": 0,
      "9 años": 0,
      "10 años": 0,
      "11-12 años": 0,
      "13-15 años": 0,
      "16 años": 0,
      "17 años": 0,
      "18 años": 0,
      "19-26 años": 0,
      "27-45 años": 0,
      "45-49 años": 0,
      "50-59 años": 0,
      "60-64 años": 0,
      ">65 años": 0
    }
  },
  {
    "codigo": 20,
    "nombre": "Fiebre amarilla",
    "edad_recomendacion": {
      "Recien nacido": 10,
      "1 mes": 10,
      "2 meses": 10,
      "4 meses": 10,
      "6 meses": 10,
      "7 meses": 10,
      "9 meses": 4,
      "12 meses": 4,
      "15 meses": 4,
      "18 meses": 6,
      "19-23 meses": 4,
      "2-3 años": 4,
      "4 años": 10,
      "5 años": 10,
      "6 años": 10,
      "7-8 años": 4,
      "9 años": 4,
      "10 años": 4,
      "11-12 años": 4,
      "13-15 años": 4,
      "16 años": 4,
      "17 años": 10,
      "18 años": 10,
      "19-26 años": 4,
      "27-45 años": 4,
      "45-49 años": 4,
      "50-59 años": 4,
      "60-64 años": 3,
      ">65 años": 3,
      ">65 años.1": 3
    },
    "condiciones_medicas": {
      "Embarazo": 2,
      "Malformación congénita del tracto gastrointestinal": 10,
      "Mujer": 10,
      "Inmunocomprometidos (Excluyndo VIH)": -1,
      "Infección VIH  Conteo CD4 <15% or <200mm3": -1,
      "Infección VIH  Conteo ≥15% and ≥200mm3": -1,
      "Asplenia, deficiencias del complemento": 10,
      "Enfermedad renal terminal o en hemodiálisis": 6,
      "Enfermedad cardíaca o enfermedad pulmonar o Alcoholismo": 10,
      "Enfermedad hepática crónica": 10,
      "Diabetes": 10,
      "Zonas endémicas": 6,
      "Personal de salud": 10,
      "Hombres que tienen relaciones sexuales con hombres": 10,
      "Alergia al huevo (Reacción severa)": 2,
      "Reacción alérgica a algun componente de la vacuna": -1,
      "Enfermedad aguda moderada o grave, con o sin fiebre": 3
    },
    "cobertura_pai": {
      "Recien nacido": 0,
      "1 mes": 0,
      "2 meses": 0,
      "4 meses": 0,
      "6 meses": 0,
      "7 meses": 0,
      "9 meses": 0,
      "12 meses": 5,
      "15 meses": 5,
      "18 meses": 1,
      "19-23 meses": 5,
      "2-3 años": 0,
      "4 años": 5,
      "5 años": 5,
      "6 años": 0,
      "7-8 años": 0,
      "9 años": 0,
      "10 años": 0,
      "11-12 años": 0,
      "13-15 años": 0,
      "16 años": 0,
      "17 años": 0,
      "18 años": 0,
      "19-26 años": 0,
      "27-45 años": 0,
      "45-49 años": 0,
      "50-59 años": 0,
      "60-64 años": 0,
      ">65 años": 0
    }
  },
  {
    "codigo": 21,
    "nombre": "Virus Sincicial RSV-mAb",
    "edad_recomendacion": {
      "Recien nacido": 6,
      "1 mes": 6,
      "2 meses": 6,
      "4 meses": 6,
      "6 meses": 6,
      "7 meses": 6,
      "9 meses": 4,
      "12 meses": 4,
      "15 meses": 4,
      "18 meses": 4,
      "19-23 meses": 10,
      "2-3 años": 10,
      "4 años": 10,
      "5 años": 10,
      "6 años": 10,
      "7-8 años": 10,
      "9 años": 10,
      "10 años": 10,
      "11-12 años": 10,
      "13-15 años": 10,
      "16 años": 10,
      "17 años": 10,
      "18 años": 10,
      "19-26 años": 10,
      "27-45 años": 10,
      "45-49 años": 10,
      "50-59 años": 10,
      "60-64 años": 10,
      ">65 años": 10,
      ">65 años.1": 10
    },
    "condiciones_medicas": {
      "Embarazo": 10,
      "Malformación congénita del tracto gastrointestinal": 10,
      "Mujer": 10,
      "Inmunocomprometidos (Excluyndo VIH)": 7,
      "Infección VIH  Conteo CD4 <15% or <200mm3": 7,
      "Infección VIH  Conteo ≥15% and ≥200mm3": 6,
      "Asplenia, deficiencias del complemento": 6,
      "Enfermedad renal terminal o en hemodiálisis": 4,
      "Enfermedad cardíaca o enfermedad pulmonar o Alcoholismo": 7,
      "Enfermedad hepática crónica": 6,
      "Diabetes": 6,
      "Zonas endémicas": 10,
      "Personal de salud": 10,
      "Hombres que tienen relaciones sexuales con hombres": 4,
      "Alergia al huevo (Reacción severa)": 10,
      "Reacción alérgica a algun componente de la vacuna": -1,
      "Enfermedad aguda moderada o grave, con o sin fiebre": 3
    },
    "cobertura_pai": {
      "Recien nacido": 0,
      "1 mes": 0,
      "2 meses": 0,
      "4 meses": 0,
      "6 meses": 0,
      "7 meses": 0,
      "9 meses": 0,
      "12 meses": 0,
      "15 meses": 0,
      "18 meses": 0,
      "19-23 meses": 0,
      "2-3 años": 0,
      "4 años": 0,
      "5 años": 0,
      "6 años": 0,
      "7-8 años": 0,
      "9 años": 0,
      "10 años": 0,
      "11-12 años": 0,
      "13-15 años": 0,
      "16 años": 0,
      "17 años": 0,
      "18 años": 0,
      "19-26 años": 0,
      "27-45 años": 0,
      "45-49 años": 0,
      "50-59 años": 0,
      "60-64 años": 0,
      ">65 años": 0
    }
  },
  {
    "codigo": 22,
    "nombre": "Viruela símica (mpox)",
    "edad_recomendacion": {
      "Recien nacido": 10,
      "1 mes": 10,
      "2 meses": 10,
      "4 meses": 10,
      "6 meses": 10,
      "7 meses": 10,
      "9 meses": 10,
      "12 meses": 10,
      "15 meses": 10,
      "18 meses": 10,
      "19-23 meses": 10,
      "2-3 años": 10,
      "4 años": 10,
      "5 años": 10,
      "6 años": 10,
      "7-8 años": 10,
      "9 años": 10,
      "10 años": 10,
      "11-12 años": 10,
      "13-15 años": 10,
      "16 años": 10,
      "17 años": 10,
      "18 años": 4,
      "19-26 años": 4,
      "27-45 años": 4,
      "45-49 años": 4,
      "50-59 años": 4,
      "60-64 años": 4,
      ">65 años": 4,
      ">65 años.1": 4
    },
    "condiciones_medicas": {
      "Embarazo": 4,
      "Malformación congénita del tracto gastrointestinal": 10,
      "Mujer": 10,
      "Inmunocomprometidos (Excluyndo VIH)": 4,
      "Infección VIH  Conteo CD4 <15% or <200mm3": 4,
      "Infección VIH  Conteo ≥15% and ≥200mm3": 4,
      "Asplenia, deficiencias del complemento": 4,
      "Enfermedad renal terminal o en hemodiálisis": 4,
      "Enfermedad cardíaca o enfermedad pulmonar o Alcoholismo": 4,
      "Enfermedad hepática crónica": 4,
      "Diabetes": 4,
      "Zonas endémicas": 10,
      "Personal de salud": 10,
      "Hombres que tienen relaciones sexuales con hombres": 10,
      "Alergia al huevo (Reacción severa)": 10,
      "Reacción alérgica a algun componente de la vacuna": -1,
      "Enfermedad aguda moderada o grave, con o sin fiebre": 3
    },
    "cobertura_pai": {
      "Recien nacido": 0,
      "1 mes": 0,
      "2 meses": 0,
      "4 meses": 0,
      "6 meses": 0,
      "7 meses": 0,
      "9 meses": 0,
      "12 meses": 0,
      "15 meses": 0,
      "18 meses": 0,
      "19-23 meses": 0,
      "2-3 años": 0,
      "4 años": 0,
      "5 años": 0,
      "6 años": 0,
      "7-8 años": 0,
      "9 años": 0,
      "10 años": 0,
      "11-12 años": 0,
      "13-15 años": 0,
      "16 años": 0,
      "17 años": 0,
      "18 años": 0,
      "19-26 años": 0,
      "27-45 años": 0,
      "45-49 años": 0,
      "50-59 años": 0,
      "60-64 años": 0,
      ">65 años": 0
    }
  },
  {
    "codigo": 23,
    "nombre": "Dengue",
    "edad_recomendacion": {
      "Recien nacido": 10,
      "1 mes": 10,
      "2 meses": 10,
      "4 meses": 10,
      "6 meses": 10,
      "7 meses": 10,
      "9 meses": 10,
      "12 meses": 10,
      "15 meses": 10,
      "18 meses": 10,
      "19-23 meses": 10,
      "2-3 años": 10,
      "4 años": 10,
      "5 años": 10,
      "6 años": 10,
      "7-8 años": 10,
      "9 años": 4,
      "10 años": 4,
      "11-12 años": 4,
      "13-15 años": 4,
      "16 años": 4,
      "17 años": 10,
      "18 años": 10,
      "19-26 años": 10,
      "27-45 años": 10,
      "45-49 años": 10,
      "50-59 años": 10,
      "60-64 años": 10,
      ">65 años": 10,
      ">65 años.1": 10
    },
    "condiciones_medicas": {
      "Embarazo": 2,
      "Malformación congénita del tracto gastrointestinal": 10,
      "Mujer": 10,
      "Inmunocomprometidos (Excluyndo VIH)": -1,
      "Infección VIH  Conteo CD4 <15% or <200mm3": -1,
      "Infección VIH  Conteo ≥15% and ≥200mm3": 2,
      "Asplenia, deficiencias del complemento": 4,
      "Enfermedad renal terminal o en hemodiálisis": 10,
      "Enfermedad cardíaca o enfermedad pulmonar o Alcoholismo": 4,
      "Enfermedad hepática crónica": 4,
      "Diabetes": 4,
      "Zonas endémicas": 10,
      "Personal de salud": 10,
      "Hombres que tienen relaciones sexuales con hombres": 10,
      "Alergia al huevo (Reacción severa)": 10,
      "Reacción alérgica a algun componente de la vacuna": -1,
      "Enfermedad aguda moderada o grave, con o sin fiebre": 3
    },
    "cobertura_pai": {
      "Recien nacido": 0,
      "1 mes": 0,
      "2 meses": 0,
      "4 meses": 0,
      "6 meses": 0,
      "7 meses": 0,
      "9 meses": 0,
      "12 meses": 0,
      "15 meses": 0,
      "18 meses": 0,
      "19-23 meses": 0,
      "2-3 años": 0,
      "4 años": 0,
      "5 años": 0,
      "6 años": 0,
      "7-8 años": 0,
      "9 años": 0,
      "10 años": 0,
      "11-12 años": 0,
      "13-15 años": 0,
      "16 años": 0,
      "17 años": 0,
      "18 años": 0,
      "19-26 años": 0,
      "27-45 años": 0,
      "45-49 años": 0,
      "50-59 años": 0,
      "60-64 años": 0,
      ">65 años": 0
    }
  },
  {
    "codigo": 24,
    "nombre": "Pentavalente (DPT-1, HB-1, Hib-1)",
    "edad_recomendacion": {
      "Recien nacido": 10,
      "1 mes": 10,
      "2 meses": 10,
      "4 meses": 10,
      "6 meses": 10,
      "7 meses": 10,
      "9 meses": 10,
      "12 meses": 10,
      "15 meses": 10,
      "18 meses": 10,
      "19-23 meses": 10,
      "2-3 años": 10,
      "4 años": 10,
      "5 años": 10,
      "6 años": 10,
      "7-8 años": 10,
      "9 años": 10,
      "10 años": 10,
      "11-12 años": 10,
      "13-15 años": 10,
      "16 años": 10,
      "17 años": 10,
      "18 años": 10,
      "19-26 años": 10,
      "27-45 años": 10,
      "45-49 años": 10,
      "50-59 años": 10,
      "60-64 años": 10,
      ">65 años": 10,
      ">65 años.1": 10
    },
    "condiciones_medicas": {
      "Embarazo": 10,
      "Malformación congénita del tracto gastrointestinal": 10,
      "Mujer": 10,
      "Inmunocomprometidos (Excluyndo VIH)": 10,
      "Infección VIH  Conteo CD4 <15% or <200mm3": 10,
      "Infección VIH  Conteo ≥15% and ≥200mm3": 10,
      "Asplenia, deficiencias del complemento": 10,
      "Enfermedad renal terminal o en hemodiálisis": 4,
      "Enfermedad cardíaca o enfermedad pulmonar o Alcoholismo": 10,
      "Enfermedad hepática crónica": 10,
      "Diabetes": 10,
      "Zonas endémicas": 10,
      "Personal de salud": 10,
      "Hombres que tienen relaciones sexuales con hombres": 10,
      "Alergia al huevo (Reacción severa)": 10,
      "Reacción alérgica a algun componente de la vacuna": -1,
      "Enfermedad aguda moderada o grave, con o sin fiebre": 3
    },
    "cobertura_pai": {
      "Recien nacido": 0,
      "1 mes": 0,
      "2 meses": 1,
      "4 meses": 1,
      "6 meses": 1,
      "7 meses": 0,
      "9 meses": 0,
      "12 meses": 5,
      "15 meses": 5,
      "18 meses": 1,
      "19-23 meses": 5,
      "2-3 años": 5,
      "4 años": 5,
      "5 años": 0,
      "6 años": 0,
      "7-8 años": 0,
      "9 años": 0,
      "10 años": 0,
      "11-12 años": 0,
      "13-15 años": 0,
      "16 años": 0,
      "17 años": 0,
      "18 años": 0,
      "19-26 años": 0,
      "27-45 años": 0,
      "45-49 años": 0,
      "50-59 años": 0,
      "60-64 años": 0,
      ">65 años": 0
    }
  },
  {
    "codigo": 25,
    "nombre": "RSV (Abrysvo)",
    "edad_recomendacion": {
      "Recien nacido": 10,
      "1 mes": 10,
      "2 meses": 10,
      "4 meses": 10,
      "6 meses": 10,
      "7 meses": 10,
      "9 meses": 10,
      "12 meses": 10,
      "15 meses": 10,
      "18 meses": 10,
      "19-23 meses": 10,
      "2-3 años": 10,
      "4 años": 10,
      "5 años": 10,
      "6 años": 10,
      "7-8 años": 10,
      "9 años": 10,
      "10 años": 10,
      "11-12 años": 4,
      "13-15 años": 4,
      "16 años": 4,
      "17 años": 4,
      "18 años": 4,
      "19-26 años": 4,
      "27-45 años": 4,
      "45-49 años": 4,
      "50-59 años": 4,
      "60-64 años": 4,
      ">65 años": 4,
      ">65 años.1": 4
    },
    "condiciones_medicas": {
      "Embarazo": 6,
      "Malformación congénita del tracto gastrointestinal": 10,
      "Mujer": 10,
      "Inmunocomprometidos (Excluyndo VIH)": 4,
      "Infección VIH  Conteo CD4 <15% or <200mm3": 4,
      "Infección VIH  Conteo ≥15% and ≥200mm3": 4,
      "Asplenia, deficiencias del complemento": 4,
      "Enfermedad renal terminal o en hemodiálisis": 4,
      "Enfermedad cardíaca o enfermedad pulmonar o Alcoholismo": 4,
      "Enfermedad hepática crónica": 4,
      "Diabetes": 4,
      "Zonas endémicas": 10,
      "Personal de salud": 10,
      "Hombres que tienen relaciones sexuales con hombres": 10,
      "Alergia al huevo (Reacción severa)": 10,
      "Reacción alérgica a algun componente de la vacuna": -1,
      "Enfermedad aguda moderada o grave, con o sin fiebre": 3
    },
    "cobertura_pai": {
      "Recien nacido": 0,
      "1 mes": 0,
      "2 meses": 0,
      "4 meses": 0,
      "6 meses": 0,
      "7 meses": 0,
      "9 meses": 0,
      "12 meses": 0,
      "15 meses": 0,
      "18 meses": 0,
      "19-23 meses": 0,
      "2-3 años": 0,
      "4 años": 0,
      "5 años": 0,
      "6 años": 0,
      "7-8 años": 0,
      "9 años": 0,
      "10 años": 0,
      "11-12 años": 0,
      "13-15 años": 0,
      "16 años": 0,
      "17 años": 0,
      "18 años": 0,
      "19-26 años": 0,
      "27-45 años": 0,
      "45-49 años": 0,
      "50-59 años": 0,
      "60-64 años": 0,
      ">65 años": 0
    }
  }
]